{
  "realmList": "anniversary",
  "timestamp": "2026-06-12T19:08:17.238Z",
  "totalRequests": 12,
  "successful": 12,
  "failed": 0,
  "results": [
    {
      "realm": "Thunderstrike",
      "faction": "Horde",
      "auctionHouseId": 560,
      "success": true,
      "timestamp": "2026-06-12T19:07:59.373Z"
    },
    {
      "realm": "Thunderstrike",
      "faction": "Alliance",
      "auctionHouseId": 559,
      "success": true,
      "timestamp": "2026-06-12T19:08:01.453Z"
    },
    {
      "realm": "Spineshatter",
      "faction": "Horde",
      "auctionHouseId": 562,
      "success": true,
      "timestamp": "2026-06-12T19:08:02.767Z"
    },
    {
      "realm": "Spineshatter",
      "faction": "Alliance",
      "auctionHouseId": 561,
      "success": true,
      "timestamp": "2026-06-12T19:08:04.279Z"
    },
    {
      "realm": "Soulseeker",
      "faction": "Horde",
      "auctionHouseId": 564,
      "success": true,
      "timestamp": "2026-06-12T19:08:06.118Z"
    },
    {
      "realm": "Soulseeker",
      "faction": "Alliance",
      "auctionHouseId": 563,
      "success": true,
      "timestamp": "2026-06-12T19:08:07.513Z"
    },
    {
      "realm": "Dreamscythe",
      "faction": "Horde",
      "auctionHouseId": 554,
      "success": true,
      "timestamp": "2026-06-12T19:08:08.906Z"
    },
    {
      "realm": "Dreamscythe",
      "faction": "Alliance",
      "auctionHouseId": 553,
      "success": true,
      "timestamp": "2026-06-12T19:08:10.252Z"
    },
    {
      "realm": "Nightslayer",
      "faction": "Horde",
      "auctionHouseId": 556,
      "success": true,
      "timestamp": "2026-06-12T19:08:11.619Z"
    },
    {
      "realm": "Nightslayer",
      "faction": "Alliance",
      "auctionHouseId": 555,
      "success": true,
      "timestamp": "2026-06-12T19:08:12.954Z"
    },
    {
      "realm": "Doomhowl",
      "faction": "Horde",
      "auctionHouseId": 558,
      "success": true,
      "timestamp": "2026-06-12T19:08:14.867Z"
    },
    {
      "realm": "Doomhowl",
      "faction": "Alliance",
      "auctionHouseId": 557,
      "success": true,
      "timestamp": "2026-06-12T19:08:16.237Z"
    }
  ]
}