{
  "realmList": "anniversary",
  "timestamp": "2026-05-08T03:31:10.990Z",
  "totalRequests": 12,
  "successful": 12,
  "failed": 0,
  "results": [
    {
      "realm": "Thunderstrike",
      "faction": "Horde",
      "auctionHouseId": 560,
      "success": true,
      "timestamp": "2026-05-08T03:30:49.401Z"
    },
    {
      "realm": "Thunderstrike",
      "faction": "Alliance",
      "auctionHouseId": 559,
      "success": true,
      "timestamp": "2026-05-08T03:30:50.902Z"
    },
    {
      "realm": "Spineshatter",
      "faction": "Horde",
      "auctionHouseId": 562,
      "success": true,
      "timestamp": "2026-05-08T03:30:52.951Z"
    },
    {
      "realm": "Spineshatter",
      "faction": "Alliance",
      "auctionHouseId": 561,
      "success": true,
      "timestamp": "2026-05-08T03:30:56.533Z"
    },
    {
      "realm": "Soulseeker",
      "faction": "Horde",
      "auctionHouseId": 564,
      "success": true,
      "timestamp": "2026-05-08T03:30:58.053Z"
    },
    {
      "realm": "Soulseeker",
      "faction": "Alliance",
      "auctionHouseId": 563,
      "success": true,
      "timestamp": "2026-05-08T03:30:59.743Z"
    },
    {
      "realm": "Dreamscythe",
      "faction": "Horde",
      "auctionHouseId": 554,
      "success": true,
      "timestamp": "2026-05-08T03:31:01.957Z"
    },
    {
      "realm": "Dreamscythe",
      "faction": "Alliance",
      "auctionHouseId": 553,
      "success": true,
      "timestamp": "2026-05-08T03:31:03.433Z"
    },
    {
      "realm": "Nightslayer",
      "faction": "Horde",
      "auctionHouseId": 556,
      "success": true,
      "timestamp": "2026-05-08T03:31:05.429Z"
    },
    {
      "realm": "Nightslayer",
      "faction": "Alliance",
      "auctionHouseId": 555,
      "success": true,
      "timestamp": "2026-05-08T03:31:06.769Z"
    },
    {
      "realm": "Doomhowl",
      "faction": "Horde",
      "auctionHouseId": 558,
      "success": true,
      "timestamp": "2026-05-08T03:31:08.208Z"
    },
    {
      "realm": "Doomhowl",
      "faction": "Alliance",
      "auctionHouseId": 557,
      "success": true,
      "timestamp": "2026-05-08T03:31:09.990Z"
    }
  ]
}