{
  "realmList": "anniversary",
  "timestamp": "2026-03-03T09:49:50.608Z",
  "totalRequests": 12,
  "successful": 12,
  "failed": 0,
  "results": [
    {
      "realm": "Thunderstrike",
      "faction": "Horde",
      "auctionHouseId": 560,
      "success": true,
      "timestamp": "2026-03-03T09:49:32.603Z"
    },
    {
      "realm": "Thunderstrike",
      "faction": "Alliance",
      "auctionHouseId": 559,
      "success": true,
      "timestamp": "2026-03-03T09:49:34.048Z"
    },
    {
      "realm": "Spineshatter",
      "faction": "Horde",
      "auctionHouseId": 562,
      "success": true,
      "timestamp": "2026-03-03T09:49:35.539Z"
    },
    {
      "realm": "Spineshatter",
      "faction": "Alliance",
      "auctionHouseId": 561,
      "success": true,
      "timestamp": "2026-03-03T09:49:36.889Z"
    },
    {
      "realm": "Soulseeker",
      "faction": "Horde",
      "auctionHouseId": 564,
      "success": true,
      "timestamp": "2026-03-03T09:49:38.290Z"
    },
    {
      "realm": "Soulseeker",
      "faction": "Alliance",
      "auctionHouseId": 563,
      "success": true,
      "timestamp": "2026-03-03T09:49:39.562Z"
    },
    {
      "realm": "Dreamscythe",
      "faction": "Horde",
      "auctionHouseId": 554,
      "success": true,
      "timestamp": "2026-03-03T09:49:41.560Z"
    },
    {
      "realm": "Dreamscythe",
      "faction": "Alliance",
      "auctionHouseId": 553,
      "success": true,
      "timestamp": "2026-03-03T09:49:42.927Z"
    },
    {
      "realm": "Nightslayer",
      "faction": "Horde",
      "auctionHouseId": 556,
      "success": true,
      "timestamp": "2026-03-03T09:49:44.353Z"
    },
    {
      "realm": "Nightslayer",
      "faction": "Alliance",
      "auctionHouseId": 555,
      "success": true,
      "timestamp": "2026-03-03T09:49:46.791Z"
    },
    {
      "realm": "Doomhowl",
      "faction": "Horde",
      "auctionHouseId": 558,
      "success": true,
      "timestamp": "2026-03-03T09:49:48.005Z"
    },
    {
      "realm": "Doomhowl",
      "faction": "Alliance",
      "auctionHouseId": 557,
      "success": true,
      "timestamp": "2026-03-03T09:49:49.607Z"
    }
  ]
}