{
  "realmList": "anniversary",
  "timestamp": "2026-03-31T07:22:02.122Z",
  "totalRequests": 12,
  "successful": 12,
  "failed": 0,
  "results": [
    {
      "realm": "Thunderstrike",
      "faction": "Horde",
      "auctionHouseId": 560,
      "success": true,
      "timestamp": "2026-03-31T07:21:45.146Z"
    },
    {
      "realm": "Thunderstrike",
      "faction": "Alliance",
      "auctionHouseId": 559,
      "success": true,
      "timestamp": "2026-03-31T07:21:46.408Z"
    },
    {
      "realm": "Spineshatter",
      "faction": "Horde",
      "auctionHouseId": 562,
      "success": true,
      "timestamp": "2026-03-31T07:21:47.926Z"
    },
    {
      "realm": "Spineshatter",
      "faction": "Alliance",
      "auctionHouseId": 561,
      "success": true,
      "timestamp": "2026-03-31T07:21:49.467Z"
    },
    {
      "realm": "Soulseeker",
      "faction": "Horde",
      "auctionHouseId": 564,
      "success": true,
      "timestamp": "2026-03-31T07:21:50.885Z"
    },
    {
      "realm": "Soulseeker",
      "faction": "Alliance",
      "auctionHouseId": 563,
      "success": true,
      "timestamp": "2026-03-31T07:21:52.356Z"
    },
    {
      "realm": "Dreamscythe",
      "faction": "Horde",
      "auctionHouseId": 554,
      "success": true,
      "timestamp": "2026-03-31T07:21:53.891Z"
    },
    {
      "realm": "Dreamscythe",
      "faction": "Alliance",
      "auctionHouseId": 553,
      "success": true,
      "timestamp": "2026-03-31T07:21:55.540Z"
    },
    {
      "realm": "Nightslayer",
      "faction": "Horde",
      "auctionHouseId": 556,
      "success": true,
      "timestamp": "2026-03-31T07:21:57.018Z"
    },
    {
      "realm": "Nightslayer",
      "faction": "Alliance",
      "auctionHouseId": 555,
      "success": true,
      "timestamp": "2026-03-31T07:21:58.437Z"
    },
    {
      "realm": "Doomhowl",
      "faction": "Horde",
      "auctionHouseId": 558,
      "success": true,
      "timestamp": "2026-03-31T07:21:59.779Z"
    },
    {
      "realm": "Doomhowl",
      "faction": "Alliance",
      "auctionHouseId": 557,
      "success": true,
      "timestamp": "2026-03-31T07:22:01.123Z"
    }
  ]
}